MANIFEST.in
README.md
setup.py
terminus/__init__.py
terminus/debian.py
terminus/interfaces.py
terminus/util.py
terminus.egg-info/PKG-INFO
terminus.egg-info/SOURCES.txt
terminus.egg-info/dependency_links.txt
terminus.egg-info/top_level.txt