Metadata-Version: 1.1
Name: terminus
Version: 0.1.2
Summary: Updates interfaces file on Debian Linux-based distros
Home-page: https://github.com/briancline/terminus
Author: Brian Cline
Author-email: brian.cline@gmail.com
License: MIT
Keywords: network interface interfaces file debian configuration
Platform: UNKNOWN
Classifier: Development Status :: 3 - Alpha
Classifier: License :: OSI Approved :: MIT License
Classifier: Intended Audience :: Developers
Classifier: Intended Audience :: System Administrators
Classifier: Natural Language :: English
Classifier: Operating System :: POSIX :: Linux
Classifier: Programming Language :: Python
Classifier: Programming Language :: Python :: 2.7
